{
  "name": "Gatsby-Deco",
  "slug": "gatsby-deco",
  "philosophy": "几何的精确、金色的奢华、仪式感与优雅。",
  "constraint": "Gold for Decoration Only (Max 5%)",
  "palette": {
    "background": "#0A1628",
    "surface": "#132238",
    "text-main": "#F5F5F0",
    "text-muted": "#A8B5C4",
    "gold": "#D4AF37",
    "secondary": "#8B4D6E"
  },
  "typography": {
    "fontFamily": {
      "display": ["Playfair Display", "Didot", "Georgia", "serif"],
      "primary": ["Lato", "Optima", "sans-serif"]
    },
    "scale": 1.414
  },
  "spacing": {
    "unit": 8,
    "scale": [8, 16, 32, 48, 80, 128]
  }
}
